Metadata-Version: 1.1
Name: py-oeis
Version: 2.0
Summary: # py-oeis
